{"ASUN": "Atlantic Sun", "America East": "America East", "American Athletic": "American Athletic", "Atlantic 10": "Atlantic 10", "Atlantic Coast": "Atlantic Coast", "Big 12": "Big 12", "Big East": "Big East", "Big Sky": "Big Sky", "Big South": "Big South", "Big West": "Big West", "Coastal Athletic Association": "Colonial Athletic Association", "Conference USA": "Conference USA", "Horizon League": "Horizon League", "Ivy League": "Ivy League", "Metro Atlantic Athletic Conference": "Metro Atlantic Athletic Conf", "Missouri Valley": "Missouri Valley", "Mountain West": "Mountain West", "Northeast": "Northeast Conf", "Ohio Valley": "Ohio Valley", "Patriot League": "Patriot League", "SEC": "SEC", "Southern": "Southern Conf", "Southland": "Southland", "Southwestern Athletic": "Southwestern Athletic", "Summit League": "Summit League", "Sun Belt": "Sun Belt", "West Coast": "West Coast", "Western Athletic": "Western Athletic", "Big Ten": "Big 10", "Independent": "Midwest Conference", "Mid-American": "Middle American Conf"}